.hgignore
.hgtags
ABOUT.txt
APACHE-LICENSE-2.0.txt
CHANGES.txt
COPYRIGHT.txt
LICENSE.txt
README.txt
TODO.txt
buildout.cfg
setup.py
tl/__init__.py
tl.buildout_apache.egg-info/PKG-INFO
tl.buildout_apache.egg-info/SOURCES.txt
tl.buildout_apache.egg-info/dependency_links.txt
tl.buildout_apache.egg-info/entry_points.txt
tl.buildout_apache.egg-info/namespace_packages.txt
tl.buildout_apache.egg-info/requires.txt
tl.buildout_apache.egg-info/top_level.txt
tl.buildout_apache.egg-info/zip-safe
tl/buildout_apache/__init__.py
tl/buildout_apache/apachectl.in
tl/buildout_apache/defaults.cfg
tl/buildout_apache/host.conf.in
tl/buildout_apache/httpd.conf.in
tl/buildout_apache/httpd.py
tl/buildout_apache/httpd.txt
tl/buildout_apache/modpython-3.3.1.patch
tl/buildout_apache/modpython.py
tl/buildout_apache/modpython.txt
tl/buildout_apache/root.py
tl/buildout_apache/root.txt
tl/buildout_apache/tests.py