Metadata-Version: 1.0
Name: tl.buildout-apache
Version: 0.3
Summary: zc.buildout recipes for setting up an Apache web server environment.
Home-page: http://www.thomas-lotze.de/en/software/buildout-recipes/
Author: Thomas Lotze
Author-email: thomas@thomas-lotze.de
License: ZPL 2.1
Keywords: buildout zc.buildout recipe apache httpd server root instance modpython mod_python
Platform: UNKNOWN
Classifier: Development Status :: 3 - Alpha
Classifier: Environment :: Console
Classifier: Environment :: Plugins
Classifier: Framework :: Buildout
Classifier: Intended Audience :: Developers
Classifier: Intended Audience :: System Administrators
Classifier: License :: OSI Approved :: Zope Public License
Classifier: Operating System :: OS Independent
Classifier: Programming Language :: Python
Classifier: Topic :: Software Development :: Build Tools
Classifier: Topic :: System :: Software Distribution
